famapy/metamodels/fm_metamodel/__init__.py
famapy/metamodels/fm_metamodel/models/__init__.py
famapy/metamodels/fm_metamodel/models/feature_model.py
famapy/metamodels/fm_metamodel/operations/__init__.py
famapy/metamodels/fm_metamodel/operations/fm_atomic_sets.py
famapy/metamodels/fm_metamodel/operations/fm_average_branching_factor.py
famapy/metamodels/fm_metamodel/operations/fm_core_features.py
famapy/metamodels/fm_metamodel/operations/fm_count_leafs.py
famapy/metamodels/fm_metamodel/operations/fm_estimated_products_number.py
famapy/metamodels/fm_metamodel/operations/fm_feature_ancestors.py
famapy/metamodels/fm_metamodel/operations/fm_leaf_features.py
famapy/metamodels/fm_metamodel/operations/fm_max_depth_tree.py
famapy/metamodels/fm_metamodel/transformations/__init__.py
famapy/metamodels/fm_metamodel/transformations/afm_reader.py
famapy/metamodels/fm_metamodel/transformations/afm_writer.py
famapy/metamodels/fm_metamodel/transformations/attributes_csv_reader.py
famapy/metamodels/fm_metamodel/transformations/featureide_reader.py
famapy/metamodels/fm_metamodel/transformations/glencoe_reader.py
famapy/metamodels/fm_metamodel/transformations/glencoe_writer.py
famapy/metamodels/fm_metamodel/transformations/json_writer.py
famapy/metamodels/fm_metamodel/transformations/splot_writer.py
famapy/metamodels/fm_metamodel/transformations/uvl_reader.py
famapy/metamodels/fm_metamodel/transformations/uvl_writer.py
famapy/metamodels/fm_metamodel/transformations/xml_reader.py
famapy_fm-1.0.0.dist-info/METADATA
famapy_fm-1.0.0.dist-info/WHEEL
famapy_fm-1.0.0.dist-info/dependency_links.txt
famapy_fm-1.0.0.dist-info/top_level.txt
famapy_fm-1.0.0.dist-info/RECORD
